dec4_16.v
//decoder 2 to 4 

module dec2_4 (W , Enable , Y);

    input [1:0] W;
    input Enable;

    output reg [0:3] Y;

    always @(W, Enable)

        case ({Enable, W})

            3’b100: Y = 4’b1000;
            3’b101: Y = 4’b0100;
            3’b110: Y = 4’b0010;
            3’b111: Y = 4’b0001;
            default: Y = 4’b0000;

        endcase

endmodule


//decoder 4 to 16 

module dec4_16 (W , Enable , Y);

    input [3:0] W;
    input Enable;

    output [0:15] Y;

    wire [0:3] T;

    dec2_4 Dec1 (W[3:2], T[0:3], Enable);
    dec2_4 Dec2 (W[1:0], Y[0:3], T[0]);
    dec2_4 Dec3 (W[1:0], Y[4:7], T[1]);
    dec2_4 Dec4 (W[1:0], Y[8:11], T[2]);
    dec2_4 Dec5 (W[1:0], Y[12:15], T[3]);

endmodule

dec4_16_tb.v
`default_nettype none
`timescale 1ps/1ps
`include "dec4_16.v"

module dec4_16_tb;

reg [3:0] W;
wire [0:15] Y;
reg Enable;

dec4_16 UUT (.W(W),  .Y(Y), .Enable(Enable));

initial begin
    $dumpfile("dec4_16_tb.vcd");
    $dumpvars(0, dec4_16_tb);


    Enable=1;

  if(Y[0]==1 || Y[1]==1 || Y[2]==1 ||Y[3]==1 ||Y[4]==1 ||Y[5]==1 ||Y[6]==1 ||Y[7]==1 ||Y[8]==1 ||
  Y[9]==1 ||Y[10]==1 ||Y[11]==1 ||Y[12]==1 ||Y[13]==1 ||Y[14]==1 ||Y[15]==1)
    $display("test fail for En=0");
  #20


    Enable=0;
    W[0] = 0;
    W[1] = 0;
    W[2] = 0;
    W[3] = 0;

            if(Y[0]!=1 || Y[1]==1 || Y[2]==1 ||Y[3]==1 ||Y[4]==1 ||Y[5]==1 ||Y[6]==1 ||Y[7]==1 ||Y[8]==1 ||
  Y[9]==1 ||Y[10]==1 ||Y[11]==1 ||Y[12]==1 ||Y[13]==1 ||Y[14]==1 ||Y[15]==1)
    $display("test fail for 0000");
  #20

  Enable=0;
    W[0] = 1;
    W[1] = 0;
    W[2] = 0;
    W[3] = 0;

  if(Y[0]==1 || Y[1]!=1 || Y[2]==1 ||Y[3]==1 ||Y[4]==1 ||Y[5]==1 ||Y[6]==1 ||Y[7]==1 ||Y[8]==1 ||
  Y[9]==1 ||Y[10]==1 ||Y[11]==1 ||Y[12]==1 ||Y[13]==1 ||Y[14]==1 ||Y[15]==1)
    $display("test fail for 0001");
  #20

    Enable=0;
    W[0] = 0;
    W[1] = 1;
    W[2] = 0;
    W[3] = 0;
 
            if(Y[0]==1 || Y[1]==1 || Y[2]!=1 ||Y[3]==1 ||Y[4]==1 ||Y[5]==1 ||Y[6]==1 ||Y[7]==1 ||Y[8]==1 ||
  Y[9]==1 ||Y[10]==1 ||Y[11]==1 ||Y[12]==1 ||Y[13]==1 ||Y[14]==1 ||Y[15]==1)
    $display("test fail for 0010");
  #20

    Enable=0;
    W[0] = 1;
    W[1] = 1;
    W[2] = 0;
    W[3] = 0;

            if(Y[0]==1 || Y[1]==1 || Y[2]==1 ||Y[3]!=1 ||Y[4]==1 ||Y[5]==1 ||Y[6]==1 ||Y[7]==1 ||Y[8]==1 ||
  Y[9]==1 ||Y[10]==1 ||Y[11]==1 ||Y[12]==1 ||Y[13]==1 ||Y[14]==1 ||Y[15]==1)
    $display("test fail for 0011");
  #20

    Enable=0;
    W[0] = 0;
    W[1] = 0;
    W[2] = 1;
    W[3] = 0;
 
            if(Y[0]==1 || Y[1]==1 || Y[2]==1 ||Y[3]==1 ||Y[4]!=1 ||Y[5]==1 ||Y[6]==1 ||Y[7]==1 ||Y[8]==1 ||
  Y[9]==1 ||Y[10]==1 ||Y[11]==1 ||Y[12]==1 ||Y[13]==1 ||Y[14]==1 ||Y[15]==1)
    $display("test fail for 0100");
  #20


    Enable=0;
    W[0] = 1;
    W[1] = 0;
    W[2] = 1;
    W[3] = 0;
 
            if(Y[0]==1 || Y[1]==1 || Y[2]==1 ||Y[3]==1 ||Y[4]==1 ||Y[5]!=1 ||Y[6]==1 ||Y[7]==1 ||Y[8]==1 ||
  Y[9]==1 ||Y[10]==1 ||Y[11]==1 ||Y[12]==1 ||Y[13]==1 ||Y[14]==1 ||Y[15]==1)
    $display("test fail for 0101");
  #20

    Enable=0;
    W[0] = 0;
    W[1] = 1;
    W[2] = 1;
    W[3] = 0;
 
            if(Y[0]==1 || Y[1]==1 || Y[2]==1 ||Y[3]==1 ||Y[4]==1 ||Y[5]==1 ||Y[6]!=1 ||Y[7]==1 ||Y[8]==1 ||
  Y[9]==1 ||Y[10]==1 ||Y[11]==1 ||Y[12]==1 ||Y[13]==1 ||Y[14]==1 ||Y[15]==1)
    $display("test fail for 0110");
  #20

    Enable=0;
    W[0] = 1;
    W[1] = 1;
    W[2] = 1;
    W[3] = 0;
 
            if(Y[0]==1 || Y[1]==1 || Y[2]==1 ||Y[3]==1 ||Y[4]==1 ||Y[5]==1 ||Y[6]==1 ||Y[7]!=1 ||Y[8]==1 ||
  Y[9]==1 ||Y[10]==1 ||Y[11]==1 ||Y[12]==1 ||Y[13]==1 ||Y[14]==1 ||Y[15]==1)
    $display("test fail for 0111");
  #20

    Enable=0;
    W[0] = 0;
    W[1] = 0;
    W[2] = 0;
    W[3] = 1;
 
            if(Y[0]==1 || Y[1]==1 || Y[2]==1 ||Y[3]==1 ||Y[4]==1 ||Y[5]==1 ||Y[6]==1 ||Y[7]==1 ||Y[8]!=1 ||
  Y[9]==1 ||Y[10]==1 ||Y[11]==1 ||Y[12]==1 ||Y[13]==1 ||Y[14]==1 ||Y[15]==1)
    $display("test fail for 1000");
  #20  


      Enable=0;
    W[0] = 1;
    W[1] = 0;
    W[2] = 0;
    W[3] = 1;
 
            if(Y[0]==1 || Y[1]==1 || Y[2]==1 ||Y[3]==1 ||Y[4]==1 ||Y[5]==1 ||Y[6]==1 ||Y[7]==1 ||Y[8]==1 ||
  Y[9]!=1 ||Y[10]==1 ||Y[11]==1 ||Y[12]==1 ||Y[13]==1 ||Y[14]==1 ||Y[15]==1)
    $display("test fail for 1001");
  #20  


        Enable=0;
    W[0] = 0;
    W[1] = 1;
    W[2] = 0;
    W[3] = 1;
 
            if(Y[0]==1 || Y[1]==1 || Y[2]==1 ||Y[3]==1 ||Y[4]==1 ||Y[5]==1 ||Y[6]==1 ||Y[7]==1 ||Y[8]==1 ||
  Y[9]==1 ||Y[10]!=1 ||Y[11]==1 ||Y[12]==1 ||Y[13]==1 ||Y[14]==1 ||Y[15]==1)
    $display("test fail for 1010");
  #20  

    Enable=0;
    W[0] = 1;
    W[1] = 1;
    W[2] = 0;
    W[3] = 1;
 
            if(Y[0]==1 || Y[1]==1 || Y[2]==1 ||Y[3]==1 ||Y[4]==1 ||Y[5]==1 ||Y[6]==1 ||Y[7]==1 ||Y[8]==1 ||
  Y[9]==1 ||Y[10]==1 ||Y[11]!=1 ||Y[12]==1 ||Y[13]==1 ||Y[14]==1 ||Y[15]==1)
    $display("test fail for 1011");
  #20  

      Enable=0;
    W[0] = 0;
    W[1] = 0;
    W[2] = 1;
    W[3] = 1;
 
            if(Y[0]==1 || Y[1]==1 || Y[2]==1 ||Y[3]==1 ||Y[4]==1 ||Y[5]==1 ||Y[6]==1 ||Y[7]==1 ||Y[8]==1 ||
  Y[9]==1 ||Y[10]==1 ||Y[11]==1 ||Y[12]!=1 ||Y[13]==1 ||Y[14]==1 ||Y[15]==1)
    $display("test fail for 1100");
  #20  


    Enable=0;
    W[0] = 1;
    W[1] = 0;
    W[2] = 1;
    W[3] = 1;
 
            if(Y[0]==1 || Y[1]==1 || Y[2]==1 ||Y[3]==1 ||Y[4]==1 ||Y[5]==1 ||Y[6]==1 ||Y[7]==1 ||Y[8]==1 ||
  Y[9]==1 ||Y[10]==1 ||Y[11]==1 ||Y[12]==1 ||Y[13]!=1 ||Y[14]==1 ||Y[15]==1)
    $display("test fail for 1101");
  #20  

      Enable=0;
    W[0] = 0;
    W[1] = 1;
    W[2] = 1;
    W[3] = 1;
 
            if(Y[0]==1 || Y[1]==1 || Y[2]==1 ||Y[3]==1 ||Y[4]==1 ||Y[5]==1 ||Y[6]==1 ||Y[7]==1 ||Y[8]==1 ||
  Y[9]==1 ||Y[10]==1 ||Y[11]==1 ||Y[12]==1 ||Y[13]==1 ||Y[14]!=1 ||Y[15]==1)
    $display("test fail for 1110");
  #20  


      Enable=0;
    W[0] = 1;
    W[1] = 1;
    W[2] = 1;
    W[3] = 1;
 
            if(Y[0]==1 || Y[1]==1 || Y[2]==1 ||Y[3]==1 ||Y[4]==1 ||Y[5]==1 ||Y[6]==1 ||Y[7]==1 ||Y[8]==1 ||
  Y[9]==1 ||Y[10]==1 ||Y[11]==1 ||Y[12]==1 ||Y[13]==1 ||Y[14]==1 ||Y[15]!=1)
    $display("test fail for 1111");
  #20  

    $display("*******complete*******");
   
end

endmodule

dec4_16_tb.vcd
$date
	Mon Nov 22 02:04:51 2021
$end
$version
	Icarus Verilog
$end
$timescale
	1ps
$end
$scope module dec4_16_tb $end
$var wire 16 ! Y [0:15] $end
$var reg 1 " Enable $end
$var reg 4 # W [3:0] $end
$scope module UUT $end
$var wire 1 " Enable $end
$var wire 4 $ W [3:0] $end
$var wire 16 % Y [0:15] $end
$var wire 4 & T [0:3] $end
$scope module Dec1 $end
$var wire 1 " Enable $end
$var wire 2 ' W [1:0] $end
$var reg 4 ( Y [0:3] $end
$upscope $end
$scope module Dec2 $end
$var wire 1 ) Enable $end
$var wire 2 * W [1:0] $end
$var reg 4 + Y [0:3] $end
$upscope $end
$scope module Dec3 $end
$var wire 1 , Enable $end
$var wire 2 - W [1:0] $end
$var reg 4 . Y [0:3] $end
$upscope $end
$scope module Dec4 $end
$var wire 1 / Enable $end
$var wire 2 0 W [1:0] $end
$var reg 4 1 Y [0:3] $end
$upscope $end
$scope module Dec5 $end
$var wire 1 2 Enable $end
$var wire 2 3 W [1:0] $end
$var reg 4 4 Y [0:3] $end
$upscope $end
$upscope $end
$upscope $end
$enddefinitions $end
#0
$dumpvars
b0 4
bx 3
02
b0 1
bx 0
0/
b0 .
bx -
0,
b0 +
bx *
0)
b0 (
bx '
b0 &
b0 %
bx $
bx #
1"
b0 !
$end
#20
b0 '
b0 *
b0 -
b0 0
b0 3
b0 #
b0 $
0"
#40
b1 *
b1 -
b1 0
b1 3
b1 #
b1 $
#60
b10 *
b10 -
b10 0
b10 3
b10 #
b10 $
#80
b11 *
b11 -
b11 0
b11 3
b11 #
b11 $
#100
b1 '
b0 *
b0 -
b0 0
b0 3
b100 #
b100 $
#120
b1 *
b1 -
b1 0
b1 3
b101 #
b101 $
#140
b10 *
b10 -
b10 0
b10 3
b110 #
b110 $
#160
b11 *
b11 -
b11 0
b11 3
b111 #
b111 $
#180
b10 '
b0 *
b0 -
b0 0
b0 3
b1000 #
b1000 $
#200
b1 *
b1 -
b1 0
b1 3
b1001 #
b1001 $
#220
b10 *
b10 -
b10 0
b10 3
b1010 #
b1010 $
#240
b11 *
b11 -
b11 0
b11 3
b1011 #
b1011 $
#260
b11 '
b0 *
b0 -
b0 0
b0 3
b1100 #
b1100 $
#280
b1 *
b1 -
b1 0
b1 3
b1101 #
b1101 $
#300
b10 *
b10 -
b10 0
b10 3
b1110 #
b1110 $
#320
b11 *
b11 -
b11 0
b11 3
b1111 #
b1111 $
