mux2_64bit.v
module mux2_64bit(w0, w1, s, f);
    input w0, w1, s;
    output reg f;

    always @(w0, w1, s)
    begin

    if (s == 0)
        f = w0;
    else
        f = w1;
    end
endmodule

mux2_64bit_tb.v
`timescale 1ps/1ps
`include "mux2_64bit.v"

module mux2_64bit_tb;

reg w0, w1, s;
wire f;

mux2_64bit uut (.w0(w0), .w1(w1), .s(s) , .f(f));

initial begin
$dumpfile("mux2_64bit_tb.vcd");
$dumpvars(0,mux2_64bit_tb);

w0=0;
w1=0;
s=0;
if(f==1)
  $display("test fail");
#20

w0=0;
w1=1;
s=0;
if(f==1)
  $display("test fail");
#20


w0=1;
w1=0;
s=0;
if(f==0)
  $display("test fail");
#20


w0=1;
w1=1;
s=0;
if(f==0)
  $display("test fail");
#20


w0=0;
w1=0;
s=1;
if(f==1)
  $display("test fail");
#20


w0=0;
w1=1;
s=1;
if(f==0)
  $display("test fail");
#20


w0=1;
w1=0;
s=1;
if(f==1)
  $display("test fail");
#20


w0=1;
w1=1;
s=1;
if(f==0)
  $display("test fail");
#20

$display("test complete");
end

endmodule

mux2_64bit_tb.vcd
$date
	Mon Nov 22 22:49:46 2021
$end
$version
	Icarus Verilog
$end
$timescale
	1ps
$end
$scope module mux2_64bit_tb $end
$var wire 1 ! f $end
$var reg 1 " s $end
$var reg 1 # w0 $end
$var reg 1 $ w1 $end
$scope module uut $end
$var wire 1 " s $end
$var wire 1 # w0 $end
$var wire 1 $ w1 $end
$var reg 1 ! f $end
$upscope $end
$upscope $end
$enddefinitions $end
#0
$dumpvars
0$
0#
0"
0!
$end
#20
1$
#40
1!
0$
1#
#60
1$
#80
0!
1"
0$
0#
#100
1!
1$
#120
0!
0$
1#
#140
1!
1$
